Metadata-Version: 2.1
Name: distribution-Package-1337
Version: 1.1
Summary: Gaussian and Binomial distributions
Author: Emmanuel Ambrose Dan
Author-email: emmanueldan@uniuyo.edu.ng
